feupy/_Course.py
feupy/_Credentials.py
feupy/_CurricularUnit.py
feupy/_Student.py
feupy/_Teacher.py
feupy/_User.py
feupy/__init__.py
feupy/_internal_utils.py
feupy/cache.py
feupy/exams.py
feupy/timetable.py
test/FeupyTestCase.py
test/__init__.py
test/testCurricularUnit.py
feupy-0.5.19.dist-info/LICENSE
feupy-0.5.19.dist-info/METADATA
feupy-0.5.19.dist-info/WHEEL
feupy-0.5.19.dist-info/top_level.txt
feupy-0.5.19.dist-info/RECORD
