Metadata-Version: 2.1
Name: feupy
Version: 0.5.19
Summary: The sigarra scraping library no one asked for
Home-page: https://github.com/up201806185/feupy
Author: Daniel Monteiro
Author-email: up201806185@fe.up.pt
License: UNKNOWN
Platform: UNKNOWN
Classifier: Development Status :: 4 - Beta
Classifier: Intended Audience :: Developers
Classifier: Programming Language :: Python :: 3
Classifier: Programming Language :: Python :: 3.6
Classifier: Programming Language :: Python :: 3.7
Classifier: Programming Language :: Python :: 3.8
Classifier: License :: OSI Approved :: MIT License
Classifier: Operating System :: OS Independent
Requires-Python: >=3.6
Requires-Dist: Pillow (==7.1.1)
Requires-Dist: beautifulsoup4 (==4.8.0)
Requires-Dist: lxml (==4.4.1)
Requires-Dist: requests (==2.22.0)
Requires-Dist: requests-futures (==1.0.0)
